weathon/__init__.py
weathon/aigc/__init__.py
weathon/aigc/semantic_functions.py
weathon/aigc/embedding/__init__.py
weathon/aigc/embedding/embedding_generator.py
weathon/aigc/memory/__init__.py
weathon/aigc/plugins/__init__.py
weathon/aigc/plugins/examples_plugins.py
weathon/aigc/plugins/search_plugins.py
weathon/aigc/search_engine/__init__.py
weathon/aigc/search_engine/bing.py
weathon/aigc/search_engine/searxng.py
weathon/aigc/services/__init__.py
weathon/aigc/services/qwen_chat_completion.py
weathon/crawler/__init__.py
weathon/crawler/hot_search.py
weathon/crawler/next_holiday.py
weathon/crawler/qinglong/__init__.py
weathon/crawler/qinglong/aliyunpan.py
weathon/crawler/qinglong/base.py
weathon/crawler/qinglong/hostloc.py
weathon/crawler/qinglong/private_tracker.py
weathon/crawler/qinglong/rain_yun.py
weathon/crawler/qinglong/tieba.py
weathon/crawler/utils/__init__.py
weathon/crawler/utils/header.py
weathon/crawler/utils/proxy.py
weathon/crawler/utils/url.py
weathon/crawler/utils/constants/__init__.py
weathon/quantization/__init__.py
weathon/quantization/data_recorder.py
weathon/quantization/application/__init__.py
weathon/quantization/application/reocrder.py
weathon/quantization/base/__init__.py
weathon/quantization/base/app.py
weathon/quantization/base/data.py
weathon/quantization/base/database.py
weathon/quantization/base/datafeed.py
weathon/quantization/base/datarecorder.py
weathon/quantization/base/gateway.py
weathon/quantization/base/engine/__init__.py
weathon/quantization/base/engine/engine.py
weathon/quantization/base/engine/event_engine.py
weathon/quantization/base/engine/main_engine.py
weathon/quantization/converter/__init__.py
weathon/quantization/converter/offset_converter.py
weathon/quantization/converter/position_holding.py
weathon/quantization/datafeed/__init__.py
weathon/quantization/datafeed/bao_stock.py
weathon/quantization/datafeed/sina.py
weathon/quantization/datafeed/tencent.py
weathon/quantization/datafeed/tu_share.py
weathon-0.0.0.32.dist-info/METADATA
weathon-0.0.0.32.dist-info/WHEEL
weathon-0.0.0.32.dist-info/entry_points.txt
weathon-0.0.0.32.dist-info/top_level.txt
weathon-0.0.0.32.dist-info/RECORD
